COPYING
COPYING.lesser
MANIFEST.in
NOTICE
README.md
requirements.txt
setup.py
compiler/__init__.py
compiler/api/__init__.py
compiler/api/compiler.py
compiler/api/source/auth_key.tl
compiler/api/source/main_api.tl
compiler/api/source/sys_msgs.tl
compiler/api/template/combinator.txt
compiler/api/template/type.txt
compiler/errors/__init__.py
compiler/errors/compiler.py
compiler/errors/sort.py
compiler/errors/source/303_SEE_OTHER.tsv
compiler/errors/source/400_BAD_REQUEST.tsv
compiler/errors/source/401_UNAUTHORIZED.tsv
compiler/errors/source/403_FORBIDDEN.tsv
compiler/errors/source/406_NOT_ACCEPTABLE.tsv
compiler/errors/source/420_FLOOD.tsv
compiler/errors/source/500_INTERNAL_SERVER_ERROR.tsv
compiler/errors/source/503_SERVICE_UNAVAILABLE.tsv
compiler/errors/template/class.txt
compiler/errors/template/sub_class.txt
cybergram/__init__.py
cybergram/client.py
cybergram/dispatcher.py
cybergram/emoji.py
cybergram/file_id.py
cybergram/filters.py
cybergram/mime_types.py
cybergram/py.typed
cybergram/sync.py
cybergram/utils.py
cybergram.egg-info/PKG-INFO
cybergram.egg-info/SOURCES.txt
cybergram.egg-info/dependency_links.txt
cybergram.egg-info/not-zip-safe
cybergram.egg-info/requires.txt
cybergram.egg-info/top_level.txt
cybergram/connection/__init__.py
cybergram/connection/connection.py
cybergram/connection/transport/__init__.py
cybergram/connection/transport/tcp/__init__.py
cybergram/connection/transport/tcp/tcp.py
cybergram/connection/transport/tcp/tcp_abridged.py
cybergram/connection/transport/tcp/tcp_abridged_o.py
cybergram/connection/transport/tcp/tcp_full.py
cybergram/connection/transport/tcp/tcp_intermediate.py
cybergram/connection/transport/tcp/tcp_intermediate_o.py
cybergram/crypto/__init__.py
cybergram/crypto/aes.py
cybergram/crypto/mtproto.py
cybergram/crypto/prime.py
cybergram/crypto/rsa.py
cybergram/enums/__init__.py
cybergram/enums/auto_name.py
cybergram/enums/chat_action.py
cybergram/enums/chat_event_action.py
cybergram/enums/chat_member_status.py
cybergram/enums/chat_members_filter.py
cybergram/enums/chat_type.py
cybergram/enums/message_entity_type.py
cybergram/enums/message_media_type.py
cybergram/enums/message_service_type.py
